MiSeCom/__init__.py
MiSeCom/configuration.py
MiSeCom/dataloader.py
MiSeCom/label_converter.py
MiSeCom/model.py
MiSeCom/pl_wrapper.py
MiSeCom/postprocess.py
MiSeCom-0.1.1.dist-info/METADATA
MiSeCom-0.1.1.dist-info/WHEEL
MiSeCom-0.1.1.dist-info/top_level.txt
MiSeCom-0.1.1.dist-info/RECORD
